panopto.py
panopto_cli-0.7.1.dist-info/LICENSE
panopto_cli-0.7.1.dist-info/METADATA
panopto_cli-0.7.1.dist-info/WHEEL
panopto_cli-0.7.1.dist-info/entry_points.txt
panopto_cli-0.7.1.dist-info/top_level.txt
panopto_cli-0.7.1.dist-info/RECORD
