Metadata-Version: 2.1
Name: panopto-cli
Version: 0.7.1
Summary: UNKNOWN
Home-page: https://github.com/harvard-dce/panopto-cli
Author: Jay Luker
Author-email: jay_luker@harvard.edu
License: Apache 2.0
Platform: UNKNOWN
Requires-Dist: Click
Requires-Dist: requests
Requires-Dist: zeep
